[
  {
    "tag_name": "entity",
    "ids_to_tags": {
      "1": "B-course",
      "2": "I-course",
      "3": "L-course",
      "4": "U-course",
      "5": "B-programme",
      "6": "I-programme",
      "7": "L-programme",
      "8": "U-programme",
      "9": "B-student",
      "10": "I-student",
      "11": "L-student",
      "12": "U-student",
      "13": "B-year",
      "14": "I-year",
      "15": "L-year",
      "16": "U-year",
      "0": "O"
    },
    "tags_to_ids": {
      "B-course": 1,
      "I-course": 2,
      "L-course": 3,
      "U-course": 4,
      "B-programme": 5,
      "I-programme": 6,
      "L-programme": 7,
      "U-programme": 8,
      "B-student": 9,
      "I-student": 10,
      "L-student": 11,
      "U-student": 12,
      "B-year": 13,
      "I-year": 14,
      "L-year": 15,
      "U-year": 16,
      "O": 0
    },
    "num_tags": 17
  }
]